soopat/__init__.py
soopat/bin/__init__.py
soopat/bin/main.py
soopat/core/__init__.py
soopat/util/__init__.py
soopat/version/version.json
soopat-1.0.1.dist-info/METADATA
soopat-1.0.1.dist-info/WHEEL
soopat-1.0.1.dist-info/entry_points.txt
soopat-1.0.1.dist-info/top_level.txt
soopat-1.0.1.dist-info/RECORD
