Metadata-Version: 2.1
Name: soopat
Version: 1.0.1
Summary: soopat pdf downloader
Home-page: https://github.com/suqingdong/soopat
Author: suqingdong
Author-email: suqingdong1114@gmail.com
License: BSD License
Project-URL: Documentation, https://soopat.readthedocs.io
Project-URL: Tracker, https://github.com/suqingdong/soopat/issues
Platform: UNKNOWN
Classifier: Development Status :: 5 - Production/Stable
Classifier: Operating System :: OS Independent
Classifier: Intended Audience :: Developers
Classifier: License :: OSI Approved :: MIT License
Classifier: Programming Language :: Python
Classifier: Programming Language :: Python :: 3
Classifier: Programming Language :: Python :: 3.8
Classifier: Topic :: Software Development :: Libraries
Requires-Dist: bs4
Requires-Dist: click
Requires-Dist: requests
Requires-Dist: passconfig
Requires-Dist: simple-loggers
